mDLDuePico/__init__.py
mDLDuePico/mDLDuePico.py
mDLDuePico-0.0.4.dist-info/METADATA
mDLDuePico-0.0.4.dist-info/WHEEL
mDLDuePico-0.0.4.dist-info/top_level.txt
mDLDuePico-0.0.4.dist-info/RECORD
