Metadata-Version: 2.1
Name: mDLDuePico
Version: 0.0.4
Summary: GHI Electronics DuePico MicroPython library.
Home-page: https://www.duelink.com/
Author: GHI Electronics
Author-email: support@ghielectronics.com
License: MIT
Classifier: Programming Language :: Python :: Implementation :: MicroPython
Requires-Dist: mDUELink
